README.md
setup.py
miraiex/__init__.py
miraiex/client.py
miraiex/endpoints.py
miraiex/markets.py
miraiex/utils.py
miraiex.egg-info/PKG-INFO
miraiex.egg-info/SOURCES.txt
miraiex.egg-info/dependency_links.txt
miraiex.egg-info/requires.txt
miraiex.egg-info/top_level.txt