Metadata-Version: 2.1
Name: miraiex
Version: 0.0.5
Summary: Python package for interacting with MiraiEx' API
Home-page: https://github.com/offish/miraiex
Author: offish
Author-email: overutilization@gmail.com
License: UNKNOWN
Download-URL: https://github.com/offish/miraiex/tarball/v0.0.5
Platform: UNKNOWN
Classifier: Programming Language :: Python :: 3
Classifier: License :: OSI Approved :: MIT License
Classifier: Operating System :: OS Independent
Requires-Python: >=3.6
